metadata.py
build_metadata-0.2.dist-info/METADATA
build_metadata-0.2.dist-info/WHEEL
build_metadata-0.2.dist-info/historia.json
build_metadata-0.2.dist-info/top_level.txt
build_metadata-0.2.dist-info/RECORD
