Metadata-Version: 2.1
Name: build-metadata
Version: 0.2
Author-email: Antti Hautaniemi <antti.hautaniemi@me.com>
License: Tekijänoikeus 2020– Antti Hautaniemi
Project-URL: Repository, https://github.com/an7oine/build-metadata.git
Requires-Python: >=3.8
Requires-Dist: build>=1.2.0
Requires-Dist: pyproject-hooks
